{
    "type": "dict",
    "collapsible": true,
    "key": "load",
    "label": "Loader plugins",
    "children": [
        {
            "type": "schema_template",
            "name": "template_loader_plugin_nuke",
            "template_data": [
                {
                    "key": "LoadImage",
                    "label": "Image Loader"
                }
            ]
        },
        {
            "type": "dict",
            "collapsible": true,
            "key": "LoadClip",
            "label": "Clip Loader",
            "checkbox_key": "enabled",
            "children": [
                {
                    "type": "boolean",
                    "key": "enabled",
                    "label": "Enabled"
                },
                {
                    "type": "list",
                    "key": "_representations",
                    "label": "Representations",
                    "object_type": "text"
                },
                {
                    "type": "text",
                    "key": "node_name_template",
                    "label": "Node name template"
                },
                {
                    "type": "splitter"
                },
                {
                    "type": "dict",
                    "collapsible": false,
                    "key": "options_defaults",
                    "label": "Loader option defaults",
                    "children": [
                        {
                            "type": "boolean",
                            "key": "start_at_workfile",
                            "label": "Start at worfile beggining"
                        },
                        {
                            "type": "boolean",
                            "key": "add_retime",
                            "label": "Add retime"
                        }
                    ]
                }
            ]
        },
        {
            "type": "dict",
            "collapsible": true,
            "key": "renderLayerLoader",
            "label": "RenderLayer Loader",
            "children": [
                {
                    "type": "text",
                    "key": "backdrop_name_template",
                    "label": "Backdrop name template"
                }
            ]
        },
        {
                    "type": "dict",
                    "collapsible": true,
                    "key": "entity_type_name_matcher",
                    "label": "Entity Type Name Matcher",
                    "children": [
                        {
                            "type": "list",
                            "key": "profiles",
                            "label": "Profiles",
                            "object_type": {
                                "type": "dict",
                                "children": [
                                    {
                                        "type": "text",
                                        "key": "entity_types",
                                        "label": "Entity Types"
                                    },
                                    {
                                        "type": "text",
                                        "key": "entity_prefix",
                                        "label": "Entity Prefix"
                                    }
                                ]
                            }
                        }
                    ]
                },
                {
                    "type": "dict",
                    "collapsible": true,
                    "key": "working_hierarchy_templates_by_tasks",
                    "label": "Working Hierarchy Templates By Tasks",
                    "children": [
                        {
                            "type": "list",
                            "key": "profiles",
                            "label": "Profiles",
                            "object_type": {
                                "type": "dict",
                                "children": [
                                    {
                                        "key": "task_types",
                                        "label": "Task types",
                                        "type": "task-types-enum"
                                    },
                                    {
                                        "key": "families",
                                        "label": "Families",
                                        "type": "list",
                                        "object_type": "text"
                                    },
                                    {
                                        "key": "templates",
                                        "label": "Templates",
                                        "type": "list",
                                        "object_type": "text"
                                    },
                                    {
                                        "type": "color",
                                        "key": "backdrop_color",
                                        "label": "Backdrop Color",
                                        "use_alpha": false
                                    }
                                ]
                            }
                        }
                    ]
                },
                {
                    "type": "dict",
                    "collapsible": true,
                    "key": "main_backdrops_manager",
                    "label": "Main Backdrops Manager",
                    "is_group": true,
                    "children": [
                        {
                            "type": "list",
                            "key": "backdrop_profiles",
                            "label": "Backdrop Profiles",
                            "object_type": {
                                "type": "dict",
                                "children": [
                                    {
                                        "key": "name",
                                        "label": "Name",
                                        "type": "text"
                                    },
                                    {
                                        "key": "color",
                                        "label": "Color",
                                        "type": "color",
                                        "use_alpha": false
                                    },
                                    {
                                        "key": "default_size",
                                        "label": "Default Size",
                                        "type": "text"
                                    },
                                    {
                                        "type": "separator"
                                    },
                                    {
                                        "key": "position",
                                        "label": "Position",
                                        "type": "enum",
                                        "multiselection": false,
                                        "defaults": "notSpec",
                                        "enum_items": [
                                            {"notSpec":  "Not Specified"},
                                            {"left": "To the Left of :"},
                                            {"right": "To the Right of :"},
                                            {"top": "On Top of :"},
                                            {"bottom":  "Under :"}
                                        ]
                                    },
                                    {
                                        "key": "backdrop_ref",
                                        "label": "Backdrop Reference",
                                        "type": "text"
                                    }
                                ]
                            }
                        }
                        ]
                }
    ]
}
